{"nodes": [{"id": "home_rsc951004_proyectos_el_imperio_docs_pendientes_md", "label": "pendientes.md", "file_type": "document", "source_file": "docs/pendientes.md", "source_location": "L1"}, {"id": "docs_pendientes_pendientes_del_proyecto", "label": "Pendientes del proyecto", "file_type": "document", "source_file": "docs/pendientes.md", "source_location": "L1"}, {"id": "docs_pendientes_narraci\u00f3n_futura", "label": "Narraci\u00f3n futura", "file_type": "document", "source_file": "docs/pendientes.md", "source_location": "L7"}, {"id": "docs_pendientes_historia_de_stigria", "label": "Historia de Stigria", "file_type": "document", "source_file": "docs/pendientes.md", "source_location": "L13"}, {"id": "docs_pendientes_instituciones_y_territorios", "label": "Instituciones y territorios", "file_type": "document", "source_file": "docs/pendientes.md", "source_location": "L31"}, {"id": "docs_pendientes_misterios_y_desarrollos_posteriores", "label": "Misterios y desarrollos posteriores", "file_type": "document", "source_file": "docs/pendientes.md", "source_location": "L46"}], "edges": [{"source": "home_rsc951004_proyectos_el_imperio_docs_pendientes_md", "target": "docs_pendientes_pendientes_del_proyecto", "relation": "contains", "confidence": "EXTRACTED", "source_file": "docs/pendientes.md", "source_location": "L1", "weight": 1.0}, {"source": "docs_pendientes_pendientes_del_proyecto", "target": "docs_pendientes_narraci\u00f3n_futura", "relation": "contains", "confidence": "EXTRACTED", "source_file": "docs/pendientes.md", "source_location": "L7", "weight": 1.0}, {"source": "docs_pendientes_pendientes_del_proyecto", "target": "docs_pendientes_historia_de_stigria", "relation": "contains", "confidence": "EXTRACTED", "source_file": "docs/pendientes.md", "source_location": "L13", "weight": 1.0}, {"source": "docs_pendientes_pendientes_del_proyecto", "target": "docs_pendientes_instituciones_y_territorios", "relation": "contains", "confidence": "EXTRACTED", "source_file": "docs/pendientes.md", "source_location": "L31", "weight": 1.0}, {"source": "docs_pendientes_pendientes_del_proyecto", "target": "docs_pendientes_misterios_y_desarrollos_posteriores", "relation": "contains", "confidence": "EXTRACTED", "source_file": "docs/pendientes.md", "source_location": "L46", "weight": 1.0}], "input_tokens": 0, "output_tokens": 0}